p123api/__init__.py
p123api/client.py
p123api-2.2.0.dist-info/LICENSE
p123api-2.2.0.dist-info/METADATA
p123api-2.2.0.dist-info/WHEEL
p123api-2.2.0.dist-info/top_level.txt
p123api-2.2.0.dist-info/RECORD
