Metadata-Version: 2.1
Name: p123api
Version: 2.2.0
Summary: Portfolio123 API wrapper
Home-page: https://github.com/portfolio-123/p123api-py
Author: Portfolio123
Author-email: info@portfolio123.com
License: UNKNOWN
Platform: UNKNOWN
Classifier: Programming Language :: Python :: 3
Classifier: License :: OSI Approved :: MIT License
Classifier: Operating System :: OS Independent
Requires-Python: >=3.6
License-File: LICENSE
Requires-Dist: pandas
Requires-Dist: requests
